mivot_validator/__init__.py
mivot_validator/annotated_votable_validator.py
mivot_validator/dmtypes_and_role_checker.py
mivot_validator/version.py
mivot_validator/xml_validator.py
mivot_validator/instance_checking/__init__.py
mivot_validator/instance_checking/inheritance_checker.py
mivot_validator/instance_checking/instance_checker.py
mivot_validator/instance_checking/instance_snippet_builder.py
mivot_validator/instance_checking/model_snippets_builder.py
mivot_validator/instance_checking/snippet_builder.py
mivot_validator/instance_checking/builder/__init__.py
mivot_validator/instance_checking/tmp_snippets/.gitkeep
mivot_validator/instance_checking/vodml/Coords-v1.0.vo-dml.xml
mivot_validator/instance_checking/vodml/Meas-v1.vo-dml.xml
mivot_validator/instance_checking/vodml/Phot-v1.1.vodml.xml
mivot_validator/instance_checking/vodml/instfov.vo-dml.xml
mivot_validator/instance_checking/vodml/mango.vo-dml.xml
mivot_validator/instance_checking/vodml/property.png
mivot_validator/instance_checking/xml_interpreter/__init__.py
mivot_validator/instance_checking/xml_interpreter/annotation_seeker.py
mivot_validator/instance_checking/xml_interpreter/att_utils.py
mivot_validator/instance_checking/xml_interpreter/dynamic_reference.py
mivot_validator/instance_checking/xml_interpreter/exceptions.py
mivot_validator/instance_checking/xml_interpreter/join_operator.py
mivot_validator/instance_checking/xml_interpreter/model_viewer.py
mivot_validator/instance_checking/xml_interpreter/resource_seeker.py
mivot_validator/instance_checking/xml_interpreter/static_reference_resolver.py
mivot_validator/instance_checking/xml_interpreter/table_iterator.py
mivot_validator/instance_checking/xml_interpreter/vocabulary.py
mivot_validator/launchers/__init__.py
mivot_validator/launchers/instance_checking_launcher.py
mivot_validator/launchers/instance_snippet_launcher.py
mivot_validator/launchers/mivot_launcher.py
mivot_validator/launchers/model_snippets_launcher.py
mivot_validator-0.6.dist-info/METADATA
mivot_validator-0.6.dist-info/WHEEL
mivot_validator-0.6.dist-info/entry_points.txt
mivot_validator-0.6.dist-info/licenses/LICENSE
mivot_validator-0.6.dist-info/RECORD
