Metadata-Version: 2.4
Name: mivot-validator
Version: 0.6
Summary: Tools for validating VOTable annotated with MIVOT and to generate MIVOT snippets
Project-URL: Homepage, https://github.com/ivoa/mivot-validator
Author-email: Laurent Michel <laurent.michel@astro.unistra.fr>
License: MIT License
License-File: LICENSE
Keywords: annotation,data model,ivoa,mivot,votable
Classifier: License :: OSI Approved :: MIT License
Classifier: Programming Language :: Python
Classifier: Programming Language :: Python :: 3
Requires-Python: >=3.6
Requires-Dist: astropy
Requires-Dist: xmlschema
Requires-Dist: xmltodict
Provides-Extra: dev
Requires-Dist: pip-tools; extra == 'dev'
Requires-Dist: pytest; extra == 'dev'
